<?xml version="1.0" encoding="UTF-8" ?>
<RULES>

    <RULE name="None" />

    <RULE name="Bash">
        <CLASS style="bold" color="blue">
            <TOKEN>alias</TOKEN>
            <TOKEN>ar</TOKEN>
            <TOKEN>asa</TOKEN>
            <TOKEN>awk</TOKEN>
            <TOKEN>banner</TOKEN>
            <TOKEN>basename</TOKEN>
            <TOKEN>bash</TOKEN>
            <TOKEN>bc</TOKEN>
            <TOKEN>break</TOKEN>
            <TOKEN>bunzip2</TOKEN>
            <TOKEN>bzip2</TOKEN>
            <TOKEN>cal</TOKEN>
            <TOKEN>case</TOKEN>
            <TOKEN>cat</TOKEN>
            <TOKEN>cd</TOKEN>
            <TOKEN>chmod</TOKEN>
            <TOKEN>cksum</TOKEN>
            <TOKEN>clear</TOKEN>
            <TOKEN>cmp</TOKEN>
            <TOKEN>cp</TOKEN>
            <TOKEN>cut</TOKEN>
            <TOKEN>date</TOKEN>
            <TOKEN>declare</TOKEN>
            <TOKEN>df</TOKEN>
            <TOKEN>diff</TOKEN>
            <TOKEN>dirname</TOKEN>
            <TOKEN>do</TOKEN>
            <TOKEN>done</TOKEN>
            <TOKEN>du</TOKEN>
            <TOKEN>echo</TOKEN>
            <TOKEN>elif</TOKEN>
            <TOKEN>else</TOKEN>
            <TOKEN>env</TOKEN>
            <TOKEN>esac</TOKEN>
            <TOKEN>eval</TOKEN>
            <TOKEN>exec</TOKEN>
            <TOKEN>exit</TOKEN>
            <TOKEN>export</TOKEN>
            <TOKEN>false</TOKEN>
            <TOKEN>fi</TOKEN>
            <TOKEN>find</TOKEN>
            <TOKEN>for</TOKEN>
            <TOKEN>function</TOKEN>
            <TOKEN>grep</TOKEN>
            <TOKEN>hash</TOKEN>
            <TOKEN>head</TOKEN>
            <TOKEN>help</TOKEN>
            <TOKEN>history</TOKEN>
            <TOKEN>id</TOKEN>
            <TOKEN>if</TOKEN>
            <TOKEN>in</TOKEN>
            <TOKEN>jobs</TOKEN>
            <TOKEN>kill</TOKEN>
            <TOKEN>local</TOKEN>
            <TOKEN>logname</TOKEN>
            <TOKEN>ls</TOKEN>
            <TOKEN>mkdir</TOKEN>
            <TOKEN>mv</TOKEN>
            <TOKEN>newgrp</TOKEN>
            <TOKEN>od</TOKEN>
            <TOKEN>paste</TOKEN>
            <TOKEN>pathchk</TOKEN>
            <TOKEN>perl</TOKEN>
            <TOKEN>print</TOKEN>
            <TOKEN>printf</TOKEN>
            <TOKEN>pwd</TOKEN>
            <TOKEN>read</TOKEN>
            <TOKEN>readonly</TOKEN>
            <TOKEN>return</TOKEN>
            <TOKEN>rm</TOKEN>
            <TOKEN>rmdir</TOKEN>
            <TOKEN>sed</TOKEN>
            <TOKEN>select</TOKEN>
            <TOKEN>set</TOKEN>
            <TOKEN>shift</TOKEN>
            <TOKEN>sleep</TOKEN>
            <TOKEN>sort</TOKEN>
            <TOKEN>source</TOKEN>
            <TOKEN>test</TOKEN>
            <TOKEN>then</TOKEN>
            <TOKEN>time</TOKEN>
            <TOKEN>touch</TOKEN>
            <TOKEN>trap</TOKEN>
            <TOKEN>true</TOKEN>
            <TOKEN>type</TOKEN>
            <TOKEN>ulimit</TOKEN>
            <TOKEN>unalias</TOKEN>
            <TOKEN>uname</TOKEN>
            <TOKEN>unset</TOKEN>
            <TOKEN>until</TOKEN>
            <TOKEN>vi</TOKEN>
            <TOKEN>vim</TOKEN>
            <TOKEN>wait</TOKEN>
            <TOKEN>which</TOKEN>
            <TOKEN>while</TOKEN>
        </CLASS>

        <!-- Strings -->
        <CLASS color="purple">
            <RANGE start='"' end='"' escape="\" />
            <RANGE start="'" end="'" escape="\" />
        </CLASS>

        <!-- Comments -->
        <CLASS color="green">
            <RANGE start="#" end="\n" />
        </CLASS>
    </RULE>

    <RULE name="PHP">
        <CLASS style="bold" color="blue">
            <TOKEN>echo</TOKEN>
            <TOKEN>foreach</TOKEN>
            <TOKEN>else</TOKEN>
            <TOKEN>if</TOKEN>
            <TOKEN>elseif</TOKEN>
            <TOKEN>for</TOKEN>
            <TOKEN>as</TOKEN>
            <TOKEN>while</TOKEN>
            <TOKEN>break</TOKEN>
            <TOKEN>continue</TOKEN>
            <TOKEN>class</TOKEN>
            <TOKEN>switch</TOKEN>
            <TOKEN>case</TOKEN>
            <TOKEN>array</TOKEN>
            <TOKEN>default</TOKEN>
            <TOKEN>do</TOKEN>
            <TOKEN>exit</TOKEN>
            <TOKEN>function</TOKEN>
            <TOKEN>global</TOKEN>
            <TOKEN>include</TOKEN>
            <TOKEN>require</TOKEN>
            <TOKEN>isset</TOKEN>
            <TOKEN>new</TOKEN>
            <TOKEN>return</TOKEN>
            <TOKEN>true</TOKEN>
            <TOKEN>false</TOKEN>
        </CLASS>

        <!-- Strings -->
        <CLASS color="purple">
            <RANGE start='"' end='"' escape="\" />
            <RANGE start="'" end="'" escape="\" />
        </CLASS>

        <!-- Comments -->
        <CLASS color="green">
            <RANGE start="//" end="\n" />
            <RANGE start="/*" end="*/" />
        </CLASS>
    </RULE>

    <RULE name="Python">
        <CLASS style="bold" color="blue">
            <TOKEN>def</TOKEN>
            <TOKEN>class</TOKEN>
            <TOKEN>if</TOKEN>
            <TOKEN>else</TOKEN>
            <TOKEN>elif</TOKEN>
            <TOKEN>for</TOKEN>
            <TOKEN>while</TOKEN>
            <TOKEN>break</TOKEN>
            <TOKEN>continue</TOKEN>
            <TOKEN>return</TOKEN>
            <TOKEN>import</TOKEN>
            <TOKEN>from</TOKEN>
            <TOKEN>as</TOKEN>
            <TOKEN>with</TOKEN>
            <TOKEN>try</TOKEN>
            <TOKEN>except</TOKEN>
            <TOKEN>raise</TOKEN>
        </CLASS>

        <!-- Strings -->
        <CLASS color="purple">
            <RANGE start='"' end='"' escape="\" />
            <RANGE start="'" end="'" escape="\" />
        </CLASS>

        <!-- Comments -->
        <CLASS color="green">
            <RANGE start="#" end="\n" />
        </CLASS>
    </RULE>

	<RULE name="Pascal">
		<!-- Palabras clave -->
		<CLASS style="bold" color="blue">
			<TOKEN>program</TOKEN>
			<TOKEN>begin</TOKEN>
			<TOKEN>end</TOKEN>
			<TOKEN>function</TOKEN>
			<TOKEN>procedure</TOKEN>
			<TOKEN>var</TOKEN>
			<TOKEN>const</TOKEN>
			<TOKEN>type</TOKEN>
			<TOKEN>integer</TOKEN>
			<TOKEN>real</TOKEN>
			<TOKEN>char</TOKEN>
			<TOKEN>string</TOKEN>
			<TOKEN>boolean</TOKEN>
			<TOKEN>record</TOKEN>
			<TOKEN>array</TOKEN>
			<TOKEN>of</TOKEN>
			<TOKEN>file</TOKEN>
			<TOKEN>set</TOKEN>
			<TOKEN>and</TOKEN>
			<TOKEN>or</TOKEN>
			<TOKEN>not</TOKEN>
			<TOKEN>xor</TOKEN>
			<TOKEN>div</TOKEN>
			<TOKEN>mod</TOKEN>
			<TOKEN>if</TOKEN>
			<TOKEN>then</TOKEN>
			<TOKEN>else</TOKEN>
			<TOKEN>case</TOKEN>
			<TOKEN>repeat</TOKEN>
			<TOKEN>until</TOKEN>
			<TOKEN>while</TOKEN>
			<TOKEN>do</TOKEN>
			<TOKEN>for</TOKEN>
			<TOKEN>to</TOKEN>
			<TOKEN>downto</TOKEN>
			<TOKEN>with</TOKEN>
		</CLASS>

		<!-- Comentarios -->
		<CLASS color="green">
			<range start="{" end="}" />
			<range start="(*" end="*)" />
			<range start="//" end="\n" />
		</CLASS>

		<!-- Strings -->
		<CLASS color="purple">
			<range start="'" end="'" escape="\" />
		</CLASS>

		<!-- Números -->
		<CLASS color="orange">
			<TOKEN>\b\d+\b</TOKEN>
		</CLASS>

		<!-- Operadores -->
		<CLASS color="red" style="bold">
			<TOKEN any="1">:=</TOKEN>
			<TOKEN any="1">=</TOKEN>
			<TOKEN any="1">&lt;</TOKEN>
			<TOKEN any="1">&gt;</TOKEN>
			<TOKEN any="1">&lt;=</TOKEN>
			<TOKEN any="1">&gt;=</TOKEN>
			<TOKEN any="1">+</TOKEN>
			<TOKEN any="1">-</TOKEN>
			<TOKEN any="1">*</TOKEN>
			<TOKEN any="1">/</TOKEN>
			<TOKEN any="1">^</TOKEN>
		</CLASS>

		<!-- Símbolos -->
		<CLASS color="blue">
			<TOKEN any="1">(</TOKEN>
			<TOKEN any="1">)</TOKEN>
			<TOKEN any="1">[</TOKEN>
			<TOKEN any="1">]</TOKEN>
			<TOKEN any="1">{</TOKEN>
			<TOKEN any="1">}</TOKEN>
			<TOKEN any="1">;</TOKEN>
			<TOKEN any="1">:</TOKEN>
			<TOKEN any="1">,</TOKEN>
			<TOKEN any="1">.</TOKEN>
		</CLASS>
	</RULE>

	<RULE name="Java/C/C++">
		<!-- Palabras clave -->
		<CLASS style="bold" color="blue">
			<TOKEN>abstract</TOKEN>
			<TOKEN>assert</TOKEN>
			<TOKEN>boolean</TOKEN>
			<TOKEN>break</TOKEN>
			<TOKEN>byte</TOKEN>
			<TOKEN>case</TOKEN>
			<TOKEN>catch</TOKEN>
			<TOKEN>char</TOKEN>
			<TOKEN>class</TOKEN>
			<TOKEN>const</TOKEN>
			<TOKEN>continue</TOKEN>
			<TOKEN>default</TOKEN>
			<TOKEN>do</TOKEN>
			<TOKEN>double</TOKEN>
			<TOKEN>else</TOKEN>
			<TOKEN>enum</TOKEN>
			<TOKEN>extends</TOKEN>
			<TOKEN>false</TOKEN>
			<TOKEN>final</TOKEN>
			<TOKEN>finally</TOKEN>
			<TOKEN>float</TOKEN>
			<TOKEN>for</TOKEN>
			<TOKEN>goto</TOKEN>
			<TOKEN>if</TOKEN>
			<TOKEN>implements</TOKEN>
			<TOKEN>import</TOKEN>
			<TOKEN>instanceof</TOKEN>
			<TOKEN>int</TOKEN>
			<TOKEN>interface</TOKEN>
			<TOKEN>long</TOKEN>
			<TOKEN>native</TOKEN>
			<TOKEN>new</TOKEN>
			<TOKEN>null</TOKEN>
			<TOKEN>package</TOKEN>
			<TOKEN>private</TOKEN>
			<TOKEN>protected</TOKEN>
			<TOKEN>public</TOKEN>
			<TOKEN>return</TOKEN>
			<TOKEN>short</TOKEN>
			<TOKEN>static</TOKEN>
			<TOKEN>strictfp</TOKEN>
			<TOKEN>super</TOKEN>
			<TOKEN>switch</TOKEN>
			<TOKEN>synchronized</TOKEN>
			<TOKEN>this</TOKEN>
			<TOKEN>throw</TOKEN>
			<TOKEN>throws</TOKEN>
			<TOKEN>transient</TOKEN>
			<TOKEN>true</TOKEN>
			<TOKEN>try</TOKEN>
			<TOKEN>void</TOKEN>
			<TOKEN>volatile</TOKEN>
			<TOKEN>while</TOKEN>
		</CLASS>

		<!-- Comentarios -->
		<CLASS color="green">
			<range start="/*" end="*/" />
			<range start="//" end="\n" />
		</CLASS>

		<!-- Strings -->
		<CLASS color="purple">
			<range start='"' end='"' escape="\" />
			<range start="'" end="'" escape="\" />
		</CLASS>

		<!-- Números -->
		<CLASS color="orange">
			<TOKEN>\b\d+(\.\d+)?\b</TOKEN>
		</CLASS>

		<!-- Operadores -->
		<CLASS color="red" style="bold">
			<TOKEN any="1">=</TOKEN>
			<TOKEN any="1">==</TOKEN>
			<TOKEN any="1">!=</TOKEN>
			<TOKEN any="1">&lt;</TOKEN>
			<TOKEN any="1">&gt;</TOKEN>
			<TOKEN any="1">&lt;=</TOKEN>
			<TOKEN any="1">&gt;=</TOKEN>
			<TOKEN any="1">+</TOKEN>
			<TOKEN any="1">-</TOKEN>
			<TOKEN any="1">*</TOKEN>
			<TOKEN any="1">/</TOKEN>
			<TOKEN any="1">%</TOKEN>
			<TOKEN any="1">&amp;&amp;</TOKEN>
			<TOKEN any="1">||</TOKEN>
			<TOKEN any="1">!</TOKEN>
			<TOKEN any="1">++</TOKEN>
			<TOKEN any="1">--</TOKEN>
			<TOKEN any="1">&amp;</TOKEN>
			<TOKEN any="1">|</TOKEN>
			<TOKEN any="1">^</TOKEN>
			<TOKEN any="1">~</TOKEN>
			<TOKEN any="1">&lt;&lt;</TOKEN>
			<TOKEN any="1">&gt;&gt;</TOKEN>
		</CLASS>

		<!-- Símbolos -->
		<CLASS color="blue">
			<TOKEN any="1">(</TOKEN>
			<TOKEN any="1">)</TOKEN>
			<TOKEN any="1">[</TOKEN>
			<TOKEN any="1">]</TOKEN>
			<TOKEN any="1">{</TOKEN>
			<TOKEN any="1">}</TOKEN>
			<TOKEN any="1">;</TOKEN>
			<TOKEN any="1">:</TOKEN>
			<TOKEN any="1">,</TOKEN>
			<TOKEN any="1">.</TOKEN>
			<TOKEN any="1">?</TOKEN>
		</CLASS>
	</RULE>

</RULES>
